floatvalidate.py
intvalidate.py
tkvalidate.py
tkvalidate-1.0.1.dist-info/METADATA
tkvalidate-1.0.1.dist-info/WHEEL
tkvalidate-1.0.1.dist-info/license.txt
tkvalidate-1.0.1.dist-info/top_level.txt
tkvalidate-1.0.1.dist-info/RECORD
