Metadata-Version: 2.1
Name: tkvalidate
Version: 1.0.1
Summary: Validation functions for tkinter Entry widgets that only allow integers or floats
Home-page: https://github.com/vinceshores
Author: Vince Shores
Author-email: vince.shores@outlook.com
License: UNKNOWN
Platform: UNKNOWN
Classifier: Intended Audience :: Developers
Classifier: License :: OSI Approved :: MIT License
Classifier: Programming Language :: Python :: 3
Classifier: Topic :: Software Development
